deepface/DeepFace.py
deepface/__init__.py
deepface/basemodels/ArcFace.py
deepface/basemodels/DeepID.py
deepface/basemodels/DlibResNet.py
deepface/basemodels/DlibWrapper.py
deepface/basemodels/Facenet.py
deepface/basemodels/Facenet512.py
deepface/basemodels/FbDeepFace.py
deepface/basemodels/OpenFace.py
deepface/basemodels/SFace.py
deepface/basemodels/VGGFace.py
deepface/basemodels/__init__.py
deepface/commons/__init__.py
deepface/commons/distance.py
deepface/commons/functions.py
deepface/commons/realtime.py
deepface/detectors/DlibWrapper.py
deepface/detectors/FaceDetector.py
deepface/detectors/MediapipeWrapper.py
deepface/detectors/MtcnnWrapper.py
deepface/detectors/OpenCvWrapper.py
deepface/detectors/RetinaFaceWrapper.py
deepface/detectors/SsdWrapper.py
deepface/detectors/YoloWrapper.py
deepface/detectors/YunetWrapper.py
deepface/detectors/__init__.py
deepface/extendedmodels/Age.py
deepface/extendedmodels/Emotion.py
deepface/extendedmodels/Gender.py
deepface/extendedmodels/Race.py
deepface/extendedmodels/__init__.py
deepface/models/__init__.py
vidizmo_deepface-0.0.1.dist-info/LICENSE
vidizmo_deepface-0.0.1.dist-info/METADATA
vidizmo_deepface-0.0.1.dist-info/WHEEL
vidizmo_deepface-0.0.1.dist-info/entry_points.txt
vidizmo_deepface-0.0.1.dist-info/top_level.txt
vidizmo_deepface-0.0.1.dist-info/RECORD
