Metadata-Version: 2.1
Name: vidizmo-deepface
Version: 0.0.1
Summary: A Lightweight Face Recognition and Facial Attribute Analysis Framework (Age, Gender, Emotion, Race) for Python
Home-page: UNKNOWN
Author: Huzaifa Tariq
Author-email: vtls.developer@vidizmo.com
License: UNKNOWN
Platform: UNKNOWN
Classifier: Programming Language :: Python :: 3
Classifier: License :: OSI Approved :: MIT License
Classifier: Operating System :: OS Independent
Requires-Python: >=3.8.0
License-File: LICENSE
